apriltag/__init__.py
apriltag/apriltag.cpython-312-x86_64-linux-musl.so
apriltag/apriltag.pyi
apriltag/apriltag_extra.py
apriltag/libapriltag.so
apriltag/libapriltag.so.3
apriltag/libapriltag.so.3.4.5
apriltag_python-3.4.5.dist-info/METADATA
apriltag_python-3.4.5.dist-info/WHEEL
apriltag_python-3.4.5.dist-info/RECORD
apriltag_python-3.4.5.dist-info/licenses/LICENSE
