Metadata-Version: 2.2
Name: apriltag-python
Version: 3.4.5
Summary: Python wrapper for the AprilTag visual fiducial detector
Author-Email: chibai <huangyibin1992@gmail.com>
License: BSD-2-Clause
Classifier: Development Status :: 5 - Production/Stable
Classifier: Intended Audience :: Developers
Classifier: Intended Audience :: Science/Research
Classifier: License :: OSI Approved :: BSD License
Classifier: Programming Language :: C
Classifier: Programming Language :: Python :: 3
Classifier: Programming Language :: Python :: 3.10
Classifier: Programming Language :: Python :: 3.11
Classifier: Programming Language :: Python :: 3.12
Classifier: Programming Language :: Python :: 3.13
Classifier: Programming Language :: Python :: 3.14
Classifier: Topic :: Scientific/Engineering :: Image Recognition
Project-URL: Homepage, https://github.com/AprilRobotics/apriltag
Project-URL: Repository, https://github.com/chibai/apriltag-python
Requires-Python: >=3.10
Requires-Dist: numpy
